nlpertools/__init__.py
nlpertools/cli.py
nlpertools/data_client.py
nlpertools/default_db_config.yml
nlpertools/get_2fa.py
nlpertools/ml.py
nlpertools/movie.py
nlpertools/nlpertools_config.yml
nlpertools/open_api.py
nlpertools/other.py
nlpertools/pic.py
nlpertools/plugin.py
nlpertools/reminder.py
nlpertools/utils_for_nlpertools.py
nlpertools/vector_index_demo.py
nlpertools/wrapper.py
nlpertools/algo/__init__.py
nlpertools/algo/ac.py
nlpertools/algo/bit_ops.py
nlpertools/algo/kmp.py
nlpertools/algo/num_ops.py
nlpertools/algo/template.py
nlpertools/algo/union.py
nlpertools/data_structure/__init__.py
nlpertools/data_structure/base_structure.py
nlpertools/dataprocess/__init__.py
nlpertools/dataprocess/dedupl.py
nlpertools/dataprocess/dp_main.py
nlpertools/draw/__init__.py
nlpertools/draw/draw.py
nlpertools/draw/math_func.py
nlpertools/io/__init__.py
nlpertools/io/dir.py
nlpertools/io/file.py
nlpertools/llm/__init__.py
nlpertools/llm/call_llm_once.py
nlpertools/llm/infer.py
nlpertools/llm/price.py
nlpertools/monitor/__init__.py
nlpertools/monitor/gpu.py
nlpertools/monitor/memory.py
nlpertools/template/__init__.py
nlpertools/utils/__init__.py
nlpertools/utils/lazy.py
nlpertools/utils/log_util.py
nlpertools/utils/package.py
nlpertools/utils/package_v1.py
nlpertools/utils/package_v2.py
nlpertools-1.0.11.dist-info/licenses/LICENSE
nlpertools_helper/__init__.py
nlpertools-1.0.11.dist-info/METADATA
nlpertools-1.0.11.dist-info/WHEEL
nlpertools-1.0.11.dist-info/entry_points.txt
nlpertools-1.0.11.dist-info/top_level.txt
nlpertools-1.0.11.dist-info/RECORD
