Metadata-Version: 2.4
Name: nlpertools
Version: 1.0.11
Summary: A small package about small basic IO operation when coding
Home-page: https://github.com/lvzii/nlpertools
Author: youshuJi
Author-email: zjs20001205@gmail.com
Project-URL: Bug Tracker, https://github.com/lvzii/nlpertools/issues
Classifier: Programming Language :: Python :: 3
Classifier: License :: OSI Approved :: MIT License
Classifier: Operating System :: OS Independent
Requires-Python: >=3.6
License-File: LICENSE
Requires-Dist: numpy
Requires-Dist: pandas
Requires-Dist: psutil
Requires-Dist: openai
Provides-Extra: torch
Requires-Dist: torch; extra == "torch"
Dynamic: license-file
Dynamic: provides-extra
Dynamic: requires-dist
